TIPN_sim_package/TIPN_PLC.py
TIPN_sim_package/__init__.py
TIPN_sim_package-0.0.1.dist-info/LICENSE
TIPN_sim_package-0.0.1.dist-info/METADATA
TIPN_sim_package-0.0.1.dist-info/WHEEL
TIPN_sim_package-0.0.1.dist-info/top_level.txt
TIPN_sim_package-0.0.1.dist-info/RECORD
